pyspi/__init__.py
pyspi/base.py
pyspi/calculator.py
pyspi/config.yaml
pyspi/data.py
pyspi/fabfour_config.yaml
pyspi/fast_config.yaml
pyspi/sonnet_config.yaml
pyspi/utils.py
pyspi/data/cml.npy
pyspi/data/cml7.npy
pyspi/data/forex.npy
pyspi/data/standard_normal.npy
pyspi/lib/__init__.py
pyspi/lib/PhiToolbox/__init__.py
pyspi/lib/PhiToolbox/Phi/__init__.py
pyspi/lib/PhiToolbox/Phi/phi_G_Gauss.m
pyspi/lib/PhiToolbox/Phi/phi_G_Gauss_AL.m
pyspi/lib/PhiToolbox/Phi/phi_G_Gauss_LBFGS.m
pyspi/lib/PhiToolbox/Phi/phi_Gauss.m
pyspi/lib/PhiToolbox/Phi/phi_comp.m
pyspi/lib/PhiToolbox/Phi/phi_comp_probs.m
pyspi/lib/PhiToolbox/Phi/phi_star_Gauss.m
pyspi/lib/PhiToolbox/utility/I_s_I_s_d.m
pyspi/lib/PhiToolbox/utility/__init__.py
pyspi/lib/PhiToolbox/utility/data_to_probs.m
pyspi/lib/PhiToolbox/utility/Gauss/Cov_comp.m
pyspi/lib/PhiToolbox/utility/Gauss/Cov_cond.m
pyspi/lib/PhiToolbox/utility/Gauss/H_gauss.m
pyspi/lib/PhiToolbox/utility/Gauss/__init__.py
pyspi/lib/PhiToolbox/utility/Gauss/logdet.m
pyspi/lib/jidt/__init__.py
pyspi/lib/jidt/infodynamics.jar
pyspi/statistics/__init__.py
pyspi/statistics/basic.py
pyspi/statistics/causal.py
pyspi/statistics/distance.py
pyspi/statistics/infotheory.py
pyspi/statistics/misc.py
pyspi/statistics/spectral.py
pyspi/statistics/wavelet.py
pyspi-2.0.1.dist-info/licenses/LICENSE.txt
pyspi-2.0.1.dist-info/METADATA
pyspi-2.0.1.dist-info/WHEEL
pyspi-2.0.1.dist-info/top_level.txt
pyspi-2.0.1.dist-info/RECORD
