Metadata-Version: 2.4
Name: pyspi
Version: 2.0.1
Summary: Library for pairwise analysis of time series data.
Home-page: https://github.com/DynamicsAndNeuralSystems/pyspi
Author: Oliver M. Cliff
Author-email: "Oliver M. Cliff" <oliver.m.cliff@gmail.com>
Maintainer: Joshua B. Moore
Maintainer-email: joshua.moore@sydney.edu.au
License: GNU General Public License v3 (GPLv3)
Project-URL: Homepage, https://github.com/DynamicsAndNeuralSystems/pyspi
Project-URL: Documentation, https://time-series-features.gitbook.io/pyspi/
Classifier: Programming Language :: Python
Classifier: Programming Language :: Python :: 3
Classifier: Development Status :: 1 - Planning
Classifier: Operating System :: POSIX :: Linux
Classifier: Intended Audience :: Science/Research
Classifier: Environment :: Console
Classifier: Environment :: Other Environment
Classifier: Topic :: Scientific/Engineering :: Physics
Classifier: Topic :: Scientific/Engineering :: Bio-Informatics
Classifier: Topic :: Scientific/Engineering :: Information Analysis
Classifier: Topic :: Scientific/Engineering :: Medical Science Apps.
Requires-Python: >=3.8
License-File: LICENSE.txt
Requires-Dist: h5py
Requires-Dist: scikit-learn
Requires-Dist: scipy
Requires-Dist: numpy<2.0.0
Requires-Dist: pandas
Requires-Dist: statsmodels
Requires-Dist: pyyaml
Requires-Dist: tqdm
Requires-Dist: nitime
Requires-Dist: hyppo
Requires-Dist: pyEDM==1.15.2.0
Requires-Dist: jpype1
Requires-Dist: sktime
Requires-Dist: dill
Requires-Dist: spectral-connectivity
Requires-Dist: torch
Requires-Dist: cdt==0.5.23
Requires-Dist: oct2py
Requires-Dist: tslearn
Requires-Dist: mne==0.23.0
Requires-Dist: seaborn
Requires-Dist: future
Requires-Dist: colorama
Provides-Extra: testing
Requires-Dist: pytest==5.4.2; extra == "testing"
Dynamic: author
Dynamic: home-page
Dynamic: license-file
Dynamic: provides-extra
Dynamic: requires-dist
